README.md
setup.cfg
setup.py
lvmanager/__init__.py
lvmanager/main.py
lvmanager/manager.py
lvmanager.egg-info/PKG-INFO
lvmanager.egg-info/SOURCES.txt
lvmanager.egg-info/dependency_links.txt
lvmanager.egg-info/entry_points.txt
lvmanager.egg-info/requires.txt
lvmanager.egg-info/top_level.txt