Metadata-Version: 2.1
Name: lvmanager
Version: 1.0
Summary: CLI tool to manage local key/certs and token.
Home-page: https://sidpremkumar.com
Author: Sid Premkumar
Author-email: sid.premkumar@gmail.com
License: MIT
Platform: UNKNOWN
